{"classes":["PROD","UPC","COLOR","NATION","SPEC","PN","PRICE","QTY","LOC"],"annotations":[["wts xiaomi redmi 10 2022 4gb/64gb carbon gray 94,00 eur 32pcs ean 6934177760600\r",{"entities":[[4,24,"PROD"],[25,33,"SPEC"],[34,45,"COLOR"],[46,55,"PRICE"],[56,61,"QTY"],[66,79,"UPC"]]}],["xiaomi redmi 10 2022 4gb/64gb sea blue 94,00 eur 125pcs ean 6934177760846\r",{"entities":[[0,20,"PROD"],[21,29,"SPEC"],[30,38,"COLOR"],[39,48,"PRICE"],[49,55,"QTY"],[60,73,"UPC"]]}],["xiaomi redmi 10 2022 4gb/64gb pebble white 94,00 eur 235pcs ean 6934177760709\r",{"entities":[[0,20,"PROD"],[21,29,"SPEC"],[30,42,"COLOR"],[43,52,"PRICE"],[53,59,"QTY"],[64,77,"UPC"]]}],["xiaomi redmi a2 2gb/32gb, light green 55,50 eur 105pcs ean 6941812721971\r",{"entities":[[0,15,"PROD"],[16,24,"SPEC"],[26,37,"COLOR"],[38,47,"PRICE"],[48,54,"QTY"],[59,72,"UPC"]]}],["xiaomi redmi a2 2gb/32gb, black 55,50 eur 145pcs ean 6941812722008\r",{"entities":[[0,15,"PROD"],[16,24,"SPEC"],[26,31,"COLOR"],[32,41,"PRICE"],[42,48,"QTY"],[53,66,"UPC"]]}],["xiaomi redmi note 10 5g 4gb/64gb graphite gray 121,00 eur 183pcs ean 6934177740701\r",{"entities":[[0,20,"PROD"],[21,32,"SPEC"],[33,46,"COLOR"],[47,57,"PRICE"],[58,64,"QTY"],[69,82,"UPC"]]}],["xiaomi redmi note 11s 4g 6gb/128gb graphite grey 148,00 eur 168pcs ean 6934177769245\r",{"entities":[[0,21,"PROD"],[22,34,"SPEC"],[35,48,"COLOR"],[49,59,"PRICE"],[60,66,"QTY"],[71,84,"UPC"]]}],["xiaomi redmi note 11s 5g 4gb/128gb star blue 148,20 eur 126pcs ean 6934177783227\r",{"entities":[[0,21,"PROD"],[22,34,"SPEC"],[35,44,"COLOR"],[45,55,"PRICE"],[56,62,"QTY"],[67,80,"UPC"]]}],["xiaomi watch s1 black 100,20 eur 259pcs ean 6934177760310",{"entities":[[0,15,"PROD"],[16,21,"COLOR"],[22,32,"PRICE"],[33,39,"QTY"],[44,57,"UPC"]]}]]}