{"classes":["PROD","UPC","COLOR","NATION","SPEC","PN","PRICE","QTY","LOC"],"annotations":[["want to sale\r",{"entities":[]}],["hp 14s-dq2079nia\r",{"entities":[[0,16,"PROD"]]}],["core i3 11th 8gb 512gb ssd 14 hd dos\r",{"entities":[[0,36,"SPEC"]]}],["hp 15s-fq4079tu\r",{"entities":[[0,15,"PN"]]}],["core i7 11th 8gb 256 gb ssd 15.6 fhd screen window 11 silver color eng keyboard.\r",{"entities":[[0,53,"SPEC"],[54,60,"COLOR"],[67,80,"SPEC"]]}],["hp probook 450 g8 ci5-1135g7/8gb/256gb ssd/15.6 /w10 pro silver color\r",{"entities":[[0,17,"PROD"],[18,56,"SPEC"],[57,69,"COLOR"]]}],["hp probook 450 g8 ci7-1165g7/8gb/256gb/ssd/webcam/15.6 fhd ips/w10 pro silver color\r",{"entities":[[0,17,"PROD"],[18,70,"SPEC"],[71,83,"COLOR"]]}],["hp pavilion x 360 convertible intel core i7 - 11th 16gb / 512gb ssd /15.6 fhd touch screen finger print reader window 11 silver.\r",{"entities":[[0,29,"PROD"],[30,120,"SPEC"],[121,128,"COLOR"]]}],["model 15-er0097nr .",{"entities":[[6,19,"PN"]]}]]}