{"classes":["PROD","UPC","COLOR","NATION","SPEC","PN","PRICE","QTY","LOC"],"annotations":[["want to buy processor\r",{"entities":[[12,21,"PROD"]]}],["i3 2nd\r",{"entities":[[0,6,"SPEC"]]}],["i3 3rd\r",{"entities":[[0,6,"SPEC"]]}],["i3 6th\r",{"entities":[[0,6,"SPEC"]]}],["i5 2nd\r",{"entities":[[0,6,"SPEC"]]}],["i5 3rd\r",{"entities":[[0,6,"SPEC"]]}],["i7 2nd\r",{"entities":[[0,6,"SPEC"]]}],["i7 3rd\r",{"entities":[[0,6,"SPEC"]]}],["i7 4th\r",{"entities":[[0,6,"SPEC"]]}],["i7 6th\r",{"entities":[[0,6,"SPEC"]]}],["i7 7th\r",{"entities":[[0,6,"SPEC"]]}],["i7 8th\r",{"entities":[[0,6,"SPEC"]]}],["i7 9th\r",{"entities":[[0,6,"SPEC"]]}],["i7 10th",{"entities":[[0,7,"SPEC"]]}]]}