{"classes":["PROD","UPC","COLOR","NATION","SPEC","PN","PRICE","QTY","LOC"],"annotations":[["want to sell\r",{"entities":[]}],["iphone 11 64gb us non\r",{"entities":[[0,9,"PROD"],[10,14,"SPEC"],[15,17,"NATION"]]}],["black 30 1520\r",{"entities":[[0,5,"COLOR"],[6,8,"QTY"],[9,13,"PRICE"]]}],["13 128gb us non\r",{"entities":[[0,2,"PROD"],[3,8,"SPEC"],[9,11,"NATION"]]}],["starlight 5 2120\r",{"entities":[[0,9,"COLOR"],[10,11,"QTY"],[12,16,"PRICE"]]}],["14 pro max 128gb us active\r",{"entities":[[0,10,"PROD"],[11,16,"SPEC"],[17,19,"NATION"]]}],["silver 1 3350\r",{"entities":[[0,6,"COLOR"],[7,8,"QTY"],[9,13,"PRICE"]]}],["14 pro max 256gb us non\r",{"entities":[[0,10,"PROD"],[11,16,"SPEC"],[17,19,"NATION"]]}],["silver 1 3600\r",{"entities":[[0,6,"COLOR"],[7,8,"QTY"],[9,13,"PRICE"]]}],["ready stock\r",{"entities":[]}],["042711773",{"entities":[]}]]}