{"classes":["PROD","UPC","COLOR","NATION","SPEC","PN","PRICE","QTY","LOC"],"annotations":[["wts\r",{"entities":[]}],["note 12 4/128 grey\r",{"entities":[[0,7,"PROD"],[8,13,"SPEC"],[14,18,"COLOR"]]}],["note 12 8/256 black/blue\r",{"entities":[[0,7,"PROD"],[8,13,"SPEC"],[14,24,"COLOR"]]}],["note 12s 8/256 black\r",{"entities":[[0,8,"PROD"],[9,14,"SPEC"],[15,20,"COLOR"]]}],["note 12 pro nfc 8/256 black\r",{"entities":[[0,11,"PROD"],[12,21,"SPEC"],[22,27,"COLOR"]]}],["redmi a1 2/32 black\r",{"entities":[[0,8,"PROD"],[9,13,"SPEC"],[14,19,"COLOR"]]}],["redmi a2 2/32 black\r",{"entities":[[0,8,"PROD"],[9,13,"SPEC"],[14,19,"COLOR"]]}],["redmi a2+ 3/64 black\r",{"entities":[[0,9,"PROD"],[10,14,"SPEC"],[15,20,"COLOR"]]}],["redmi 9a 2/32 grey/green\r",{"entities":[[0,8,"PROD"],[9,13,"SPEC"],[14,24,"COLOR"]]}],["redmi 10a 2/32 blue\r",{"entities":[[0,9,"PROD"],[10,14,"SPEC"],[15,19,"COLOR"]]}],["redmi 12c 3/64 grey\r",{"entities":[[0,9,"PROD"],[10,14,"SPEC"],[15,19,"COLOR"]]}],["redmi 10 2022 4/128 grey/blue/white\r",{"entities":[[0,13,"PROD"],[14,19,"SPEC"],[20,35,"COLOR"]]}],["poco c40 3/32 grey/green/yellow\r",{"entities":[[0,8,"PROD"],[9,13,"SPEC"],[14,31,"COLOR"]]}],["pm price prices",{"entities":[]}]]}