{"classes":["PROD","UPC","COLOR","NATION","SPEC","PN","PRICE","QTY","LOC"],"annotations":[["wts\r",{"entities":[]}],["hp 650g1\r",{"entities":[[0,2,"PROD"],[3,8,"PN"]]}],["ci7-4th\r",{"entities":[[0,7,"SPEC"]]}],["8/500\r",{"entities":[[0,5,"SPEC"]]}],["grade a\r",{"entities":[]}],["400pcs+\r",{"entities":[[0,7,"QTY"]]}],[".\r",{"entities":[]}],["wts\r",{"entities":[]}],["dell 7480 touch 2k\r",{"entities":[[0,4,"PROD"],[5,9,"PN"],[10,18,"SPEC"]]}],["ci7-7th\r",{"entities":[[0,7,"SPEC"]]}],["8/256\r",{"entities":[[0,5,"SPEC"]]}],["a+\r",{"entities":[]}],["quantity available\r",{"entities":[]}],["contact with me for the price..\r",{"entities":[]}],["hossam.. +971507356695",{"entities":[]}]]}